ragstack_ragulate/__init__.py
ragstack_ragulate/analysis.py
ragstack_ragulate/cli.py
ragstack_ragulate/cli_commands/__init__.py
ragstack_ragulate/cli_commands/compare.py
ragstack_ragulate/cli_commands/download.py
ragstack_ragulate/cli_commands/ingest.py
ragstack_ragulate/cli_commands/query.py
ragstack_ragulate/cli_commands/run.py
ragstack_ragulate/config/__init__.py
ragstack_ragulate/config/base_config_schema.py
ragstack_ragulate/config/config_parser.py
ragstack_ragulate/config/config_schema_0_1.py
ragstack_ragulate/config/objects.py
ragstack_ragulate/config/utils.py
ragstack_ragulate/datasets/__init__.py
ragstack_ragulate/datasets/base_dataset.py
ragstack_ragulate/datasets/crag_dataset.py
ragstack_ragulate/datasets/llama_dataset.py
ragstack_ragulate/datasets/utils.py
ragstack_ragulate/framework.py
ragstack_ragulate/logging_config.py
ragstack_ragulate/pipelines/__init__.py
ragstack_ragulate/pipelines/base_pipeline.py
ragstack_ragulate/pipelines/feedbacks.py
ragstack_ragulate/pipelines/ingest_pipeline.py
ragstack_ragulate/pipelines/query_pipeline.py
ragstack_ragulate/utils.py
ragstack_ai_ragulate-0.0.13.dist-info/METADATA
ragstack_ai_ragulate-0.0.13.dist-info/WHEEL
ragstack_ai_ragulate-0.0.13.dist-info/entry_points.txt
ragstack_ai_ragulate-0.0.13.dist-info/RECORD
