Metadata-Version: 2.1
Name: ragstack-ai-ragulate
Version: 0.0.13
Summary: A tool for evaluating RAG pipelines
Home-page: https://github.com/datastax/ragstack-ai
License: Apache 2.0
Author: DataStax
Requires-Python: >=3.10,<3.13
Classifier: License :: Other/Proprietary License
Classifier: Programming Language :: Python :: 3
Classifier: Programming Language :: Python :: 3.10
Classifier: Programming Language :: Python :: 3.11
Classifier: Programming Language :: Python :: 3.12
Requires-Dist: aiofiles (>=24.1.0,<25.0.0)
Requires-Dist: cerberus (>=1.3.5,<2.0.0)
Requires-Dist: inflection (>=0.5.1,<0.6.0)
Requires-Dist: kaleido (==0.2.1)
Requires-Dist: llama-index-core (>=0.10.31,<0.11.0)
Requires-Dist: numpy (>=1.23.5)
Requires-Dist: pandas (>=2.2.2)
Requires-Dist: plotly (>=5.22.0,<6.0.0)
Requires-Dist: pydantic (>=2.7.4,<3.0.0)
Requires-Dist: python-dotenv (>=1.0.0)
Requires-Dist: pyyaml (>=6.0.1,<7.0.0)
Requires-Dist: seaborn (>=0.13.2,<0.14.0)
Requires-Dist: setuptools (>=70.0.0,<71.0.0)
Requires-Dist: tqdm (>=4.66.1)
Requires-Dist: trulens-eval (>=0.31)
Project-URL: Documentation, https://docs.datastax.com/en/ragstack
Project-URL: Repository, https://github.com/datastax/ragstack-ai
